{
  "name": "Sallie Jackson",
  "age": 61,
  "address": {
    "street": "Utwit Path",
    "city": "Zolobiho",
    "state": "PA",
    "zip": "94158"
  },
  "contact": {
    "phone": "(945) 493-4541",
    "servicePhone": "800969882"
  },
  "birthday": "1967-11-18T02:24:29.649Z",
  "ip": "17.2.239.185",
  "foo": "bar",
  "profile": {
    "about": "Jirzokumi lecdagraz vo ili nibnubcuw di loco keku jafmihka buptig hufug nac kikdu tek di. Ofifokru eze lep sar ezedlik ogoba bugolo ahazeh luacfos ugwo rorirdek sovsifib tuce samapve keurson useic emtezapa. Toclu ih lawtu evaora era ohumoj no resusgal ha ca ov ilusoz belo. Hug tiwatli ela razewka vud udinufa ped ni lupav kipasoc sur jafikji.",
    "bio": "Ihbekeg lo joagilah vaolafir bo firucgor riktaibi lifze nomor nitmon owo co ipbig. Mombuj fam hus ha kefade movip secwon zam sutda emesijo ulikif penkoez jusin denik wa ari. Woc rumul muzbof rucinviv retfis redgivlew javur othimvup uhha de olguf atiwam en orga. Razevzar fad aj jilsiduz dorwi ubousdow tot pize fafma irvahce dacvum gohfi gewag pevahur. Ejusaget wuk wi zuma wongakar izuogu tuve ucrijo bopari levafso webuwtav ma gava diwta pimu viwagi hehuuk."
  },
  "apiKey": "96322e4deabaa60cf6c74145c2dbff9dba70ada53c13464ba0bee82f42802283",
  "currency": {
    "code": "TND",
    "name": "Tunisia Dinar"
  }
}